pelican_katex/__init__.py
pelican_katex/katex.js
pelican_katex/markdown.py
pelican_katex/plugin.py
pelican_katex/render-katex.js
pelican_katex/rendering.py
pelican_katex/restructuredtext.py
pelican_katex-1.8.2.dist-info/LICENSE
pelican_katex-1.8.2.dist-info/WHEEL
pelican_katex-1.8.2.dist-info/METADATA
pelican_katex-1.8.2.dist-info/RECORD
