Metadata-Version: 2.1
Name: pelican-katex
Version: 1.8.2
Summary: LaTeX pre-rendering for pelican with katex.js
Author-email: Marten Lienen <marten.lienen@gmail.com>
Requires-Python: >= 3.6
Classifier: License :: OSI Approved :: GNU General Public License v3 (GPLv3)
Classifier: Programming Language :: Python :: 3
Classifier: Framework :: Pelican :: Plugins
Classifier: Development Status :: 5 - Production/Stable
Classifier: Intended Audience :: Developers
Classifier: Intended Audience :: Science/Research
Classifier: Intended Audience :: Education
Requires-Dist: pelican
Requires-Dist: docutils
Requires-Dist: markdown ; extra == "markdown"
Requires-Dist: pytest ; extra == "test"
Requires-Dist: markdown ; extra == "test"
Requires-Dist: lxml ; extra == "test"
Project-URL: homepage, https://github.com/martenlienen/pelican-katex
Provides-Extra: markdown
Provides-Extra: test
